{
  "hash": "b805fa87",
  "configHash": "865e03e4",
  "lockfileHash": "0ee84dd6",
  "browserHash": "34cb3635",
  "optimized": {
    "react": {
      "src": "../../node_modules/react/index.js",
      "file": "react.js",
      "fileHash": "477006c9",
      "needsInterop": true
    },
    "react-dom/client": {
      "src": "../../node_modules/react-dom/client.js",
      "file": "react-dom_client.js",
      "fileHash": "59d40d97",
      "needsInterop": true
    },
    "react-router-dom": {
      "src": "../../node_modules/react-router-dom/dist/index.js",
      "file": "react-router-dom.js",
      "fileHash": "a4395267",
      "needsInterop": false
    },
    "react-icons/fa": {
      "src": "../../node_modules/react-icons/fa/index.mjs",
      "file": "react-icons_fa.js",
      "fileHash": "9bdd6476",
      "needsInterop": false
    },
    "react-icons/md": {
      "src": "../../node_modules/react-icons/md/index.mjs",
      "file": "react-icons_md.js",
      "fileHash": "bee8a240",
      "needsInterop": false
    },
    "react-icons/ti": {
      "src": "../../node_modules/react-icons/ti/index.mjs",
      "file": "react-icons_ti.js",
      "fileHash": "f1f4284c",
      "needsInterop": false
    },
    "react-icons/fi": {
      "src": "../../node_modules/react-icons/fi/index.mjs",
      "file": "react-icons_fi.js",
      "fileHash": "922be93f",
      "needsInterop": false
    },
    "react-icons/hi": {
      "src": "../../node_modules/react-icons/hi/index.mjs",
      "file": "react-icons_hi.js",
      "fileHash": "98e13779",
      "needsInterop": false
    },
    "react-icons/ri": {
      "src": "../../node_modules/react-icons/ri/index.mjs",
      "file": "react-icons_ri.js",
      "fileHash": "96d4d0ac",
      "needsInterop": false
    },
    "react-icons/io5": {
      "src": "../../node_modules/react-icons/io5/index.mjs",
      "file": "react-icons_io5.js",
      "fileHash": "7f888018",
      "needsInterop": false
    },
    "react-icons/io": {
      "src": "../../node_modules/react-icons/io/index.mjs",
      "file": "react-icons_io.js",
      "fileHash": "0992974a",
      "needsInterop": false
    }
  },
  "chunks": {
    "chunk-QPG7G3M7": {
      "file": "chunk-QPG7G3M7.js"
    },
    "chunk-VXRM46ES": {
      "file": "chunk-VXRM46ES.js"
    },
    "chunk-UTEJFLXC": {
      "file": "chunk-UTEJFLXC.js"
    }
  }
}